init_provider/__init__.py
init_provider/decorators.py
init_provider/decorators.pyi
init_provider/exceptions.py
init_provider/provider.py
init_provider/_internal/__init__.py
init_provider/_internal/_metaclass.py
init_provider/_internal/_utils.py
init_provider-0.1.3.dist-info/METADATA
init_provider-0.1.3.dist-info/WHEEL
init_provider-0.1.3.dist-info/licenses/LICENSE
init_provider-0.1.3.dist-info/RECORD
