Metadata-Version: 2.4
Name: init-provider
Version: 0.1.3
Project-URL: Homepage, https://github.com/vduseev/init-provider
Project-URL: Documentation, https://github.com/vduseev/init-provider
Project-URL: Repository, https://github.com/vduseev/init-provider
Project-URL: Issues, https://github.com/vduseev/init-provider/issues
Author-email: vduseev <vagiz@duseev.com>
Maintainer-email: vduseev <vagiz@duseev.com>
License-Expression: Apache-2.0
License-File: LICENSE
Keywords: dependency,initialization,lifecycle,provider,singleton
Classifier: Development Status :: 4 - Beta
Classifier: Intended Audience :: Developers
Classifier: License :: OSI Approved :: Apache Software License
Classifier: Programming Language :: Python :: 3
Classifier: Programming Language :: Python :: 3.10
Classifier: Programming Language :: Python :: 3.11
Classifier: Programming Language :: Python :: 3.12
Classifier: Programming Language :: Python :: 3.13
Classifier: Programming Language :: Python :: 3.14
Classifier: Topic :: Software Development :: Libraries
Classifier: Topic :: Software Development :: Libraries :: Application Frameworks
Classifier: Topic :: Software Development :: Libraries :: Python Modules
Requires-Python: >=3.10
